KiMoPack/__init__.py
KiMoPack/_version.py
KiMoPack/plot_func.py
kimopack-7.13.5.dist-info/LICENSE
kimopack-7.13.5.dist-info/METADATA
kimopack-7.13.5.dist-info/WHEEL
kimopack-7.13.5.dist-info/top_level.txt
kimopack-7.13.5.dist-info/RECORD
