Metadata-Version: 2.1
Name: KiMoPack
Version: 7.13.5
Summary: A comprehensive package for the analysis of kinetic data.
Author-email: Jens Uhlig <jens.uhlig@chemphys.lu.se>
Project-URL: Bug Tracker, https://github.com/erdzeichen/KiMoPack/issues
Project-URL: Repository, https://github.com/erdzeichen/KiMoPack
Project-URL: Homepage, https://www.chemphys.lu.se/research/projects/kimopack/
Project-URL: Documentation, https://kimopack.readthedocs.io/
Classifier: Programming Language :: Python :: 3
Classifier: License :: OSI Approved :: GNU General Public License v3 (GPLv3)
Classifier: Operating System :: OS Independent
Classifier: Development Status :: 5 - Production/Stable
Classifier: Natural Language :: English
Classifier: Topic :: Scientific/Engineering :: Chemistry
Classifier: Topic :: Scientific/Engineering :: Information Analysis
Classifier: Topic :: Scientific/Engineering :: Physics
Classifier: Framework :: Jupyter
Requires-Python: >=3.8
License-File: LICENSE
Requires-Dist: pandas>=1.4
Requires-Dist: tables
Requires-Dist: tabulate
Requires-Dist: h5py>=3.1
Requires-Dist: matplotlib>=3.3
Requires-Dist: numpy>=1.19
Requires-Dist: lmfit>=1.0
Requires-Dist: scipy>=1.5
Requires-Dist: pathlib
Requires-Dist: urllib3
